get_block
