Metadata-Version: 2.1
Name: get-block
Version: 0.0.2
Summary: Get details about a block provided in hex
Home-page: UNKNOWN
Author: Hawk94
Author-email: tom@miller.mx
License: MIT
Keywords: ethereum validator
Platform: UNKNOWN
Classifier: Development Status :: 4 - Beta
Classifier: License :: OSI Approved :: MIT License
Classifier: Programming Language :: Python :: 3.9
Classifier: Topic :: Utilities
License-File: LICENSE
